demo/__init__.py
demo/rotate_stuff.py
demo/transform_stuff.py
pose3d/__init__.py
pose3d/er.py
pose3d/et.py
pose3d/pose.py
pose3d/transform.py
pose3d/transform_set.py
pose3d/utils.py
pose3d-2.1.0.dist-info/LICENSE
pose3d-2.1.0.dist-info/METADATA
pose3d-2.1.0.dist-info/WHEEL
pose3d-2.1.0.dist-info/top_level.txt
pose3d-2.1.0.dist-info/RECORD
