Metadata-Version: 2.1
Name: pose3d
Version: 2.1.0
Summary: Transforming and handling 3D poses and frames.
Author: John Halazonetis
Author-email: <john.halazonetis@icloud.com>
Project-URL: Documentation, https://johnhal.gitlab.io/pose3d_python
Project-URL: Repository, https://gitlab.com/johnhal/pose3d_python
Keywords: python,pose,transform
Classifier: Intended Audience :: Developers
Classifier: Programming Language :: Python :: 3
Classifier: Operating System :: Unix
Classifier: Operating System :: MacOS :: MacOS X
Classifier: Operating System :: Microsoft :: Windows
License-File: LICENSE
Requires-Dist: numpy
Requires-Dist: scipy
Requires-Dist: pandas
Requires-Dist: toml
